color_wallpaper/ColorWallpaper.py
color_wallpaper/__init__.py
color_wallpaper/__main__.py
color_wallpaper/cli.py
color_wallpaper/color.py
color_wallpaper/common.py
color_wallpaper/data.py
color_wallpaper/font.png
color_wallpaper-1.1.9.data/data/color_wallpaper/font.png
color_wallpaper-1.1.9.dist-info/LICENSE
color_wallpaper-1.1.9.dist-info/METADATA
color_wallpaper-1.1.9.dist-info/WHEEL
color_wallpaper-1.1.9.dist-info/top_level.txt
color_wallpaper-1.1.9.dist-info/RECORD
