Metadata-Version: 2.1
Name: color-wallpaper
Version: 1.1.9
Summary: A Minimalist wallpaper generator
Home-page: https://github.com/BranislavBajuzik/ColorWallpaper
Author: TheAl_T
Author-email: branislav.bajuzik@gmail.com
License: GPLv3
Keywords: wallpaper color minimalist
Platform: UNKNOWN
Classifier: Development Status :: 5 - Production/Stable
Classifier: Intended Audience :: End Users/Desktop
Classifier: License :: OSI Approved :: GNU General Public License v3 (GPLv3)
Classifier: Operating System :: OS Independent
Classifier: Programming Language :: Python :: 3
Classifier: Topic :: Multimedia :: Graphics
Requires-Python: >=3.6
Requires-Dist: Pillow
